MANIFEST.in
README.md
pyproject.toml
setup.cfg
setup.py
c/_robustats.c
c/base.c
c/base.h
c/robustats.c
c/robustats.h
robustats/__init__.py
robustats/robustats.py
robustats.egg-info/PKG-INFO
robustats.egg-info/SOURCES.txt
robustats.egg-info/dependency_links.txt
robustats.egg-info/requires.txt
robustats.egg-info/top_level.txt