Metadata-Version: 2.1
Name: robustats
Version: 0.1.6
Summary: Robustats is a Python library for high-performance computation of robust statistical estimators.
Home-page: https://github.com/FilippoBovo/robustats
Author: Filippo Bovo
Author-email: bovo.filippo@gmail.com
License: MIT
Download-URL: https://github.com/FilippoBovo/robustats/archive/v0.1.5.tar.gz
Platform: UNKNOWN
Classifier: Programming Language :: Python :: 3
